{"version":"0.2.0","name":"game-site-client","dependencies":{"@emotion/react":{"version":"11.10.5"},"@emotion/styled":{"version":"11.10.5"},"@mui/icons-material":{"version":"5.11.0"},"@mui/material":{"version":"5.11.6"},"@stomp/stompjs":{"version":"6.1.2"},"@testing-library/jest-dom":{"version":"5.16.5"},"@testing-library/react":{"version":"13.4.0"},"@testing-library/user-event":{"version":"14.4.3"},"@types/jest":{"version":"29.4.0"},"@types/node":{"version":"18.11.18"},"@types/react-dom":{"version":"18.0.10"},"@types/react-router":{"version":"5.1.20"},"@types/react":{"version":"18.0.27"},"@types/sockjs-client":{"version":"1.5.1"},"@types/stompjs":{"version":"2.3.5"},"axios":{"version":"1.2.6"},"react-dom":{"version":"18.2.0"},"react-router-dom":{"version":"6.8.0"},"react-router":{"version":"6.8.0"},"react-scripts":{"version":"5.0.1"},"react":{"version":"18.2.0"},"sockjs-client":{"version":"1.6.1"},"ts-transformer-keys":{"version":"0.4.4"},"typescript-rest-client":{"version":"1.0.37"},"typescript":{"version":"4.9.4"},"web-vitals":{"version":"3.1.1"}}}